prisms_jobs/__init__.py
prisms_jobs/config.py
prisms_jobs/job.py
prisms_jobs/jobdb.py
prisms_jobs/misc.py
prisms_jobs/templates.py
prisms_jobs/interface/__init__.py
prisms_jobs/interface/default.py
prisms_jobs/interface/slurm.py
prisms_jobs/interface/torque.py
prisms_jobs/scripts/__init__.py
prisms_jobs/scripts/pstat.py
prisms_jobs/scripts/psub.py
prisms_jobs/scripts/taskmaster.py
prisms_jobs-4.0.3.data/data/LICENSE
prisms_jobs-4.0.3.data/data/requirements.txt
prisms_jobs-4.0.3.dist-info/LICENSE
prisms_jobs-4.0.3.dist-info/METADATA
prisms_jobs-4.0.3.dist-info/WHEEL
prisms_jobs-4.0.3.dist-info/entry_points.txt
prisms_jobs-4.0.3.dist-info/top_level.txt
prisms_jobs-4.0.3.dist-info/RECORD
