Metadata-Version: 2.1
Name: prisms-jobs
Version: 4.0.3
Summary: Job submission and management
Home-page: https://prisms-center.github.io/prisms_jobs_docs/
Author: PRISMS Center and CASM developers
Author-email: casm-developers@lists.engr.ucsb.edu
License: LGPL2.1+
Platform: UNKNOWN
Classifier: Development Status :: 4 - Beta
Classifier: License :: OSI Approved :: GNU Lesser General Public License v2 or later (LGPLv2+)
Classifier: Programming Language :: Python
Classifier: Programming Language :: Python :: 2.7
Classifier: Programming Language :: Python :: 3
Classifier: Topic :: Scientific/Engineering
Classifier: Topic :: System :: Distributed Computing
Requires-Python: >=2.7
Requires-Dist: future
Requires-Dist: six
